flask_strip_whitespace/middlewares/__init__.py
flask_strip_whitespace-0.1.0.dist-info/LICENSE
flask_strip_whitespace-0.1.0.dist-info/METADATA
flask_strip_whitespace-0.1.0.dist-info/WHEEL
flask_strip_whitespace-0.1.0.dist-info/RECORD
