Metadata-Version: 2.1
Name: flask-strip-whitespace
Version: 0.1.0
Summary: A powerful HTML whitespace remover for Flask
License: GPLv3
Author: baseplate-admin
Author-email: 61817579+baseplate-admin@users.noreply.github.com
Requires-Python: >=3.7,<4.0
Classifier: License :: Other/Proprietary License
Classifier: Programming Language :: Python :: 3
Classifier: Programming Language :: Python :: 3.7
Classifier: Programming Language :: Python :: 3.8
Classifier: Programming Language :: Python :: 3.9
Classifier: Programming Language :: Python :: 3.10
Classifier: Programming Language :: Python :: 3.11
Requires-Dist: flask (>=2.2.2,<3.0.0)
Requires-Dist: python-strip-whitespace (>=0.1.0,<0.2.0)
